MANIFEST.in
README.rst
setup.cfg
setup.py
fitsne/__init__.py
fitsne/_version.py
fitsne/cppwrap.cpp
fitsne/cppwrap.pyx
fitsne/cywrap.py
fitsne.egg-info/PKG-INFO
fitsne.egg-info/SOURCES.txt
fitsne.egg-info/dependency_links.txt
fitsne.egg-info/requires.txt
fitsne.egg-info/top_level.txt
fitsne/src/.tsne.cpp.swp
fitsne/src/ProgressBar.hpp
fitsne/src/annoylib.h
fitsne/src/kissrandom.h
fitsne/src/nbodyfft.cpp
fitsne/src/nbodyfft.h
fitsne/src/parallel_for.h
fitsne/src/sptree.cpp
fitsne/src/sptree.h
fitsne/src/time_code.h
fitsne/src/tsne.cpp
fitsne/src/tsne.h
fitsne/src/vptree.h
test/test.py