Metadata-Version: 1.1
Name: fitsne
Version: 1.2.1
Summary: Fast Fourier Transform-accelerated Interpolation-based t-SNE (FIt-SNE)
Home-page: https://github.com/KlugerLab/FIt-SNE
Author: George Linderman, Gioele La Manno
Author-email: george.linderman@gmail.com, gioelelamanno@gmail.com
License: BSD3
Download-URL: https://github.com/KlugerLab/pyFIt-SNE/archive/1.2.1.tar.gz
Keywords: tSNE,embedding
Platform: UNKNOWN
